modnet/__init__.py
modnet/ext_data.py
modnet/preprocessing.py
modnet/sklearn.py
modnet/utils.py
modnet/data/Features_cross
modnet/featurizers/__init__.py
modnet/featurizers/featurizers.py
modnet/featurizers/utils.py
modnet/featurizers/presets/__init__.py
modnet/featurizers/presets/debreuck_2020.py
modnet/hyper_opt/__init__.py
modnet/hyper_opt/fit_genetic.py
modnet/matbench/__init__.py
modnet/matbench/benchmark.py
modnet/model_presets/__init__.py
modnet/model_presets/presets.py
modnet/models/__init__.py
modnet/models/bayesian.py
modnet/models/ensemble.py
modnet/models/vanilla.py
modnet/tests/__init__.py
modnet/tests/conftest.py
modnet/tests/test_benchmark.py
modnet/tests/test_ext_data.py
modnet/tests/test_hyper_opt.py
modnet/tests/test_model.py
modnet/tests/test_preprocessing.py
modnet/tests/test_sklearn.py
modnet-0.1.13.dist-info/LICENSE.md
modnet-0.1.13.dist-info/METADATA
modnet-0.1.13.dist-info/WHEEL
modnet-0.1.13.dist-info/top_level.txt
modnet-0.1.13.dist-info/RECORD
