Metadata-Version: 2.1
Name: modnet
Version: 0.1.13
Summary: MODNet, the Material Optimal Descriptor Network for materials properties prediction. 
Home-page: https://github.com/ppdebreuck/modnet
Author: Pierre-Paul De Breuck
Author-email: pierre-paul.debreuck@uclouvain.be
Project-URL: GitHub, https://github.com/ppdebreuck/modnet
Project-URL: Documentation, https://modnet.readthedocs.io
Classifier: Programming Language :: Python :: 3.8
Classifier: Intended Audience :: Science/Research
Classifier: Topic :: Scientific/Engineering :: Information Analysis
Classifier: Topic :: Scientific/Engineering :: Physics
Classifier: Topic :: Scientific/Engineering :: Chemistry
Classifier: Topic :: Software Development :: Libraries :: Python Modules
Classifier: License :: OSI Approved :: MIT License
Classifier: Operating System :: OS Independent
Requires-Python: >=3.8
License-File: LICENSE.md
Requires-Dist: pandas (>=0.25.3)
Requires-Dist: tensorflow (>=2.4)
Requires-Dist: tensorflow-probability (>=0.12)
Requires-Dist: pymatgen (<2020.9,>=2020)
Requires-Dist: matminer (>=0.6.2)
Requires-Dist: numpy (>=1.18.3)
Requires-Dist: scikit-learn (<0.24,>=0.23)
Provides-Extra: dev
Requires-Dist: pre-commit (~=2.11) ; extra == 'dev'
Provides-Extra: test
Requires-Dist: pytest (>=6.0) ; extra == 'test'
Requires-Dist: pytest-cov (>=2.10) ; extra == 'test'
Requires-Dist: flake8 (>=3.8) ; extra == 'test'
